TracWikinfo-0.2.dist-info/DESCRIPTION.rst
TracWikinfo-0.2.dist-info/METADATA
TracWikinfo-0.2.dist-info/RECORD
TracWikinfo-0.2.dist-info/WHEEL
TracWikinfo-0.2.dist-info/entry_points.txt
TracWikinfo-0.2.dist-info/metadata.json
TracWikinfo-0.2.dist-info/top_level.txt
wikinfo/__init__.py
wikinfo/macro.py
