Metadata-Version: 2.0
Name: TracWikinfo
Version: 0.2
Summary: Provides a few useful macros to get data about wiki pages
Home-page: https://trac-hacks.org/WikinfoPlugin
Author: Ryan J Ollos
Author-email: ryan.j.ollos@gmail.com
License: 3-Clause BSD
Keywords: trac wiki info macro
Platform: UNKNOWN
